tricircle/__init__.py
tricircle/api/__init__.py
tricircle/api/app.py
tricircle/api/opts.py
tricircle/api/wsgi.py
tricircle/api/controllers/__init__.py
tricircle/api/controllers/job.py
tricircle/api/controllers/pod.py
tricircle/api/controllers/root.py
tricircle/api/controllers/routing.py
tricircle/cmd/__init__.py
tricircle/cmd/api.py
tricircle/cmd/manage.py
tricircle/cmd/status.py
tricircle/cmd/xjob.py
tricircle/common/__init__.py
tricircle/common/baserpc.py
tricircle/common/client.py
tricircle/common/config.py
tricircle/common/constants.py
tricircle/common/context.py
tricircle/common/exceptions.py
tricircle/common/httpclient.py
tricircle/common/i18n.py
tricircle/common/lock_handle.py
tricircle/common/opts.py
tricircle/common/policy.py
tricircle/common/request_source.py
tricircle/common/resource_handle.py
tricircle/common/restapp.py
tricircle/common/rpc.py
tricircle/common/serializer.py
tricircle/common/topics.py
tricircle/common/utils.py
tricircle/common/version.py
tricircle/common/xrpcapi.py
tricircle/db/__init__.py
tricircle/db/api.py
tricircle/db/core.py
tricircle/db/migration_helpers.py
tricircle/db/models.py
tricircle/db/opts.py
tricircle/db/migrate_repo/__init__.py
tricircle/db/migrate_repo/migrate.cfg
tricircle/db/migrate_repo/versions/001_init.py
tricircle/db/migrate_repo/versions/002_resource.py
tricircle/db/migrate_repo/versions/003_shadow_agent.py
tricircle/db/migrate_repo/versions/004_fix_resource_routings_pod_id_length.py
tricircle/db/migrate_repo/versions/005_fix_cached_endpoints_pod_id_length.py
tricircle/db/migrate_repo/versions/006_add_project_id_to_async_jobs.py
tricircle/db/migrate_repo/versions/007_add_project_id_to_async_job_logs.py
tricircle/db/migrate_repo/versions/008_fix_shadow_agents_pod_id_length.py
tricircle/db/migrate_repo/versions/009_recycle_resources.py
tricircle/db/migrate_repo/versions/010_add_resource_routings_bottom_id_index.py
tricircle/db/migrate_repo/versions/011_add_deleting_resources.py
tricircle-8.0.0.dist-info/AUTHORS
tricircle-8.0.0.dist-info/LICENSE
tricircle-8.0.0.dist-info/METADATA
tricircle-8.0.0.dist-info/WHEEL
tricircle-8.0.0.dist-info/entry_points.txt
tricircle-8.0.0.dist-info/pbr.json
tricircle-8.0.0.dist-info/top_level.txt
tricircle-8.0.0.dist-info/RECORD
