Metadata-Version: 2.1
Name: tricircle
Version: 8.0.0
Summary: The Tricircle is to provide networking automation across Neutron in multi-region OpenStack deployments.
Home-page: https://docs.openstack.org/tricircle/latest/
Author: OpenStack
Author-email: openstack-discuss@lists.openstack.org
License: UNKNOWN
Platform: UNKNOWN
Classifier: Environment :: OpenStack
Classifier: Intended Audience :: Information Technology
Classifier: Intended Audience :: System Administrators
Classifier: License :: OSI Approved :: Apache Software License
Classifier: Operating System :: POSIX :: Linux
Classifier: Programming Language :: Python
Classifier: Programming Language :: Python :: 3
Classifier: Programming Language :: Python :: 3.6
Classifier: Programming Language :: Python :: 3.7
Requires-Dist: pbr (!=2.1.0,>=4.0.0)
Requires-Dist: Babel (!=2.4.0,>=2.3.4)
Requires-Dist: Paste (>=2.0.2)
Requires-Dist: PasteDeploy (>=1.5.0)
Requires-Dist: Routes (>=2.3.1)
Requires-Dist: debtcollector (>=1.19.0)
Requires-Dist: eventlet (!=0.18.3,!=0.20.1,>=0.18.2)
Requires-Dist: pecan (!=1.0.2,!=1.0.3,!=1.0.4,!=1.2,>=1.3.2)
Requires-Dist: requests (>=2.14.2)
Requires-Dist: Jinja2 (>=2.10)
Requires-Dist: keystonemiddleware (>=4.17.0)
Requires-Dist: netaddr (>=0.7.18)
Requires-Dist: netifaces (>=0.10.4)
Requires-Dist: SQLAlchemy (!=1.1.5,!=1.1.6,!=1.1.7,!=1.1.8,>=1.2.0)
Requires-Dist: WebOb (>=1.8.2)
Requires-Dist: python-cinderclient (>=3.3.0)
Requires-Dist: python-glanceclient (>=2.8.0)
Requires-Dist: python-keystoneclient (>=3.8.0)
Requires-Dist: python-neutronclient (>=6.7.0)
Requires-Dist: python-novaclient (>=9.1.0)
Requires-Dist: alembic (>=0.8.10)
Requires-Dist: six (>=1.10.0)
Requires-Dist: stevedore (>=1.20.0)
Requires-Dist: oslo.concurrency (>=3.26.0)
Requires-Dist: oslo.config (>=5.2.0)
Requires-Dist: oslo.context (>=2.19.2)
Requires-Dist: oslo.db (>=4.37.0)
Requires-Dist: oslo.i18n (>=3.15.3)
Requires-Dist: oslo.log (>=3.36.0)
Requires-Dist: oslo.messaging (>=5.29.0)
Requires-Dist: oslo.middleware (>=3.31.0)
Requires-Dist: oslo.policy (>=1.30.0)
Requires-Dist: oslo.rootwrap (>=5.8.0)
Requires-Dist: oslo.serialization (!=2.19.1,>=2.18.0)
Requires-Dist: oslo.service (!=1.28.1,>=1.24.0)
Requires-Dist: oslo.upgradecheck (>=0.1.1)
Requires-Dist: oslo.utils (>=3.33.0)
Requires-Dist: sqlalchemy-migrate (>=0.11.0)
Requires-Dist: neutron (>=12.0.0)
Requires-Dist: networking-sfc (>=8.0.0.0b1)
